Metadata-Version: 2.1
Name: pythoncheck
Version: 0.0.3
Summary: First Simple Python package
Home-page: https://github.com/knop-k/pythoncheck
Author: Krzysiek
Author-email: admin@example.com
License: MIT license
Keywords: pythoncheck
Classifier: Intended Audience :: Developers
Classifier: License :: OSI Approved :: MIT License
Classifier: Natural Language :: English
Classifier: Programming Language :: Python :: 3
Classifier: Programming Language :: Python :: 3.8
Classifier: Programming Language :: Python :: 3.9
Classifier: Programming Language :: Python :: 3.10
Classifier: Programming Language :: Python :: 3.11
Requires-Python: >=3.8
License-File: LICENSE
License-File: AUTHORS.rst
